mido/__init__.py
mido/frozen.py
mido/parser.py
mido/ports.py
mido/sockets.py
mido/syx.py
mido/tokenizer.py
mido/version.py
mido/backends/__init__.py
mido/backends/_parser_queue.py
mido/backends/amidi.py
mido/backends/backend.py
mido/backends/portmidi.py
mido/backends/portmidi_init.py
mido/backends/pygame.py
mido/backends/rtmidi.py
mido/backends/rtmidi_python.py
mido/backends/rtmidi_utils.py
mido/messages/__init__.py
mido/messages/checks.py
mido/messages/decode.py
mido/messages/encode.py
mido/messages/messages.py
mido/messages/specs.py
mido/messages/strings.py
mido/midifiles/__init__.py
mido/midifiles/meta.py
mido/midifiles/midifiles.py
mido/midifiles/tracks.py
mido/midifiles/units.py
mido/scripts/__init__.py
mido/scripts/mido_connect.py
mido/scripts/mido_play.py
mido/scripts/mido_ports.py
mido/scripts/mido_serve.py
mido-1.3.3.dist-info/LICENSE
mido-1.3.3.dist-info/METADATA
mido-1.3.3.dist-info/WHEEL
mido-1.3.3.dist-info/entry_points.txt
mido-1.3.3.dist-info/top_level.txt
mido-1.3.3.dist-info/RECORD
