Metadata-Version: 2.1
Name: mido
Version: 1.3.3
Summary: MIDI Objects for Python
Author-email: Ole Martin Bjorndalen <ombdalen@gmail.com>
Maintainer-email: Radovan Bast <radovan.bast@gmail.com>, Raphaël Doursenaud <rdoursenaud@gmail.com>
License: MIT
Project-URL: documentation, https://mido.readthedocs.io
Project-URL: source, https://github.com/mido/mido
Keywords: python,midi,midifile
Classifier: Development Status :: 5 - Production/Stable
Classifier: Intended Audience :: Developers
Classifier: Natural Language :: English
Classifier: License :: OSI Approved :: MIT License
Classifier: Programming Language :: Python
Classifier: Programming Language :: Python :: 3 :: Only
Classifier: Programming Language :: Python :: 3.7
Classifier: Programming Language :: Python :: 3.8
Classifier: Programming Language :: Python :: 3.9
Classifier: Programming Language :: Python :: 3.10
Classifier: Programming Language :: Python :: 3.11
Classifier: Programming Language :: Python :: 3.12
Classifier: Programming Language :: Python :: 3.13
Classifier: Topic :: Multimedia :: Sound/Audio :: MIDI
Classifier: Topic :: Software Development
Classifier: Topic :: Software Development :: Libraries
Classifier: Topic :: Software Development :: Libraries :: Python Modules
Classifier: Topic :: Utilities
Requires-Python: ~=3.7
Provides-Extra: build-docs
Provides-Extra: check-manifest
Provides-Extra: lint-code
Provides-Extra: lint-reuse
Provides-Extra: ports-pygame
Provides-Extra: ports-rtmidi
Provides-Extra: ports-rtmidi-python
Provides-Extra: release
Provides-Extra: test-code
Provides-Extra: dev
Provides-Extra: ports-all
License-File: LICENSE
